JavaLib/JavaLib.py
JavaLib/__init__.py
JavaLib/main.py
JavaLib-0.1.dist-info/LICENSE
JavaLib-0.1.dist-info/METADATA
JavaLib-0.1.dist-info/WHEEL
JavaLib-0.1.dist-info/top_level.txt
JavaLib-0.1.dist-info/RECORD
