Metadata-Version: 2.1
Name: JavaLib
Version: 0.1
Summary: JavaLib is a Python library that provides several functions and classes to manipulate strings and count the number of elements, using Java language terms.
Home-page: https://github.com/ArizalMuluk/JavaLib
Author: Arizal Firdaus
Author-email: bangmulukkeren@gmail.com
License: UNKNOWN
Platform: UNKNOWN
Classifier: Programming Language :: Python :: 3
Classifier: License :: OSI Approved :: Apache Software License
Classifier: Operating System :: OS Independent
Requires-Python: >=3.10
License-File: LICENSE
